regchain/__about__.py
regchain/__init__.py
regchain/cli.py
regchain/core.py
regchain/audit/__init__.py
regchain/audit/base.py
regchain/audit/jsonl.py
regchain/policies/__init__.py
regchain/policies/base.py
regchain/policies/escalation.py
regchain/policies/pii.py
regchain/policies/reasons.py
regchain/policies/schema.py
regchain/utils/memo.py
regchain-0.0.1.dist-info/METADATA
regchain-0.0.1.dist-info/WHEEL
regchain-0.0.1.dist-info/entry_points.txt
regchain-0.0.1.dist-info/licenses/LICENSE
regchain-0.0.1.dist-info/RECORD
