Metadata-Version: 2.4
Name: regchain
Version: 0.0.1
Summary: Governance, audit, evaluation, and controls for AI workflows in regulated finance.
Project-URL: Homepage, https://github.com/prashant-fintech/regchain
Project-URL: Issues, https://github.com/prashant-fintech/regchain/issues
Author: Prashant Singh
License: MIT License
License-File: LICENSE
Keywords: ai-governance,audit,banking,decisioning,model-risk,mrm
Classifier: License :: OSI Approved :: MIT License
Classifier: Operating System :: OS Independent
Classifier: Programming Language :: Python :: 3
Requires-Python: >=3.10
Requires-Dist: pydantic>=2.7
Provides-Extra: credit
Requires-Dist: joblib>=1.3; extra == 'credit'
Requires-Dist: numpy>=1.26; extra == 'credit'
Requires-Dist: pandas>=2.1; extra == 'credit'
Requires-Dist: scikit-learn>=1.3; extra == 'credit'
Provides-Extra: dev
Requires-Dist: pytest>=8.0; extra == 'dev'
Requires-Dist: ruff>=0.5; extra == 'dev'
